web_anno_tsv/__init__.py
web_anno_tsv/web_anno_tsv.py
web_anno_tsv-0.0.1.dist-info/METADATA
web_anno_tsv-0.0.1.dist-info/WHEEL
web_anno_tsv-0.0.1.dist-info/top_level.txt
web_anno_tsv-0.0.1.dist-info/RECORD
