Metadata-Version: 2.1
Name: web-anno-tsv
Version: 0.0.1
Summary: Read and an write web anno tsv
Home-page: https://github.com/Pangeamt/web_anno_tsv
Author: Laurent Bié
Author-email: l.bie@pangeanic.com
License: UNKNOWN
Platform: UNKNOWN
Classifier: Programming Language :: Python :: 3
Classifier: License :: OSI Approved :: MIT License
Classifier: Operating System :: OS Independent
Requires-Python: >=3.7
